synthatdelays/AirportDelay.py
synthatdelays/Analysis.py
synthatdelays/AuxFunctions.py
synthatdelays/Classes.py
synthatdelays/EnRouteDelay.py
synthatdelays/PaxLinking.py
synthatdelays/PriorityQueue.py
synthatdelays/Scenarios.py
synthatdelays/SynthATDelays.py
synthatdelays/__init__.py
synthatdelays/data/__init__.py
synthatdelays/data/realDelaysEDDF.npz
synthatdelays/data/realDelaysEGLL.npz
synthatdelays/data/realDelaysEHAM.npz
synthatdelays/data/realDelaysLEMD.npz
synthatdelays/data/realDelaysLFPG.npz
synthatdelays-1.0.2.dist-info/licenses/LICENSE
synthatdelays-1.0.2.dist-info/METADATA
synthatdelays-1.0.2.dist-info/WHEEL
synthatdelays-1.0.2.dist-info/top_level.txt
synthatdelays-1.0.2.dist-info/RECORD
