Metadata-Version: 2.4
Name: synthatdelays
Version: 1.0.2
Summary: A library with a minimal model of operations between airports, designed to synthesise realistic time series of delays and operations.
Author: Carlson Büth
Author-email: Massimiliano Zanin <massimiliano.zanin@gmail.com>
License-Expression: AGPL-3.0-only
Project-URL: Homepage, https://gitlab.com/MZanin/synth-at-delays
Project-URL: Issues, https://gitlab.com/MZanin/synth-at-delays/issues
Project-URL: Documentation, https://gitlab.com/MZanin/synth-at-delays/-/wikis/home
Project-URL: Repository, https://gitlab.com/MZanin/synth-at-delays
Project-URL: Changelog, https://gitlab.com/MZanin/synth-at-delays/-/wikis/Home/Version-History
Keywords: air transport,flight delays,simulation,synthetic data,aviation research
Classifier: Programming Language :: Python :: 3
Classifier: Programming Language :: Python :: 3.11
Classifier: Programming Language :: Python :: 3.12
Classifier: Programming Language :: Python :: 3.13
Classifier: Programming Language :: Python :: 3.14
Classifier: Operating System :: OS Independent
Classifier: Intended Audience :: Science/Research
Classifier: Natural Language :: English
Requires-Python: >=3.11
License-File: LICENSE
Requires-Dist: numpy>=2.0.0
Requires-Dist: statsmodels
Provides-Extra: lint
Requires-Dist: ruff; extra == "lint"
Provides-Extra: test
Requires-Dist: pytest; extra == "test"
Requires-Dist: pytest-cov; extra == "test"
Requires-Dist: coverage; extra == "test"
Provides-Extra: tutorials
Requires-Dist: matplotlib; extra == "tutorials"
Provides-Extra: all
Requires-Dist: synthatdelays[lint,test,tutorials]; extra == "all"
Dynamic: license-file
